{
    "ambientocclusion": false,
    "textures": {
        "all": "minecraft:block/spruce_planks",
        "particle": "minecraft:block/spruce_planks"
    },
    "elements": [
        {
            "from": [
                3,
                0,
                0
            ],
            "to": [
                5,
                16,
                16
            ],
            "faces": {
                "north": {
                    "uv": [
                        0,
                        0,
                        2,
                        16
                    ],
                    "texture": "#all"
                },
                "east": {
                    "uv": [
                        0,
                        0,
                        2,
                        16
                    ],
                    "texture": "#all"
                },
                "south": {
                    "uv": [
                        0,
                        0,
                        16,
                        16
                    ],
                    "texture": "#all"
                },
                "west": {
                    "uv": [
                        0,
                        0,
                        16,
                        16
                    ],
                    "texture": "#all"
                },
                "up": {
                    "uv": [
                        0,
                        0,
                        2,
                        16
                    ],
                    "texture": "#all"
                },
                "down": {
                    "uv": [
                        0,
                        0,
                        2,
                        16
                    ],
                    "texture": "#all"
                }
            }
        },
        {
            "from": [
                11,
                0,
                0
            ],
            "to": [
                13,
                16,
                16
            ],
            "faces": {
                "north": {
                    "uv": [
                        0,
                        0,
                        2,
                        16
                    ],
                    "texture": "#all"
                },
                "east": {
                    "uv": [
                        0,
                        0,
                        2,
                        16
                    ],
                    "texture": "#all"
                },
                "south": {
                    "uv": [
                        0,
                        0,
                        16,
                        16
                    ],
                    "texture": "#all"
                },
                "west": {
                    "uv": [
                        0,
                        0,
                        16,
                        16
                    ],
                    "texture": "#all"
                },
                "up": {
                    "uv": [
                        0,
                        0,
                        2,
                        16
                    ],
                    "texture": "#all"
                },
                "down": {
                    "uv": [
                        0,
                        0,
                        2,
                        16
                    ],
                    "texture": "#all"
                }
            }
        }
    ]
}