{
  "type": "minecraft:crafting_shapeless",
  "ingredients": [
    { "item": "materia:charcoal_gray_string" },
    { "item": "materia:charcoal_gray_string" },
    { "item": "materia:charcoal_gray_string" },
    { "item": "materia:charcoal_gray_string" },
    { "item": "materia:charcoal_gray_string" },
    { "item": "materia:charcoal_gray_string" },
    { "item": "materia:charcoal_gray_string" },
    { "item": "materia:charcoal_gray_string" },
    { "tag": "materia:all_needles" }
  ],
  "result": { "item": "materia:charcoal_gray_carpet", "count": 1 }
}
